TSB_UAD/__init__.py
TSB_UAD/models/AE.py
TSB_UAD/models/__init__.py
TSB_UAD/models/cnn.py
TSB_UAD/models/damp.py
TSB_UAD/models/detectorA.py
TSB_UAD/models/detectorB.py
TSB_UAD/models/distance.py
TSB_UAD/models/feature.py
TSB_UAD/models/hbos.py
TSB_UAD/models/iforest.py
TSB_UAD/models/lof.py
TSB_UAD/models/lstm.py
TSB_UAD/models/matrix_profile.py
TSB_UAD/models/ocsvm.py
TSB_UAD/models/pca.py
TSB_UAD/models/poly.py
TSB_UAD/models/sand.py
TSB_UAD/models/sklearn_base.py
TSB_UAD/transformer/__init__.py
TSB_UAD/transformer/artificialConstruction.py
TSB_UAD/transformer/sbd_distance.py
TSB_UAD/transformer/transformer.py
TSB_UAD/utils/__init__.py
TSB_UAD/utils/slidingWindows.py
TSB_UAD/utils/stat_models.py
TSB_UAD/utils/utility.py
TSB_UAD/utils/visualisation.py
TSB_UAD/vus/__init__.py
TSB_UAD/vus/basic_metrics.py
TSB_UAD/vus/metrics.py
TSB_UAD/vus/affiliation/__init__.py
TSB_UAD/vus/affiliation/_affiliation_zone.py
TSB_UAD/vus/affiliation/_integral_interval.py
TSB_UAD/vus/affiliation/_single_ground_truth_event.py
TSB_UAD/vus/affiliation/generics.py
TSB_UAD/vus/affiliation/metrics.py
TSB_UAD/vus/utils/__init__.py
TSB_UAD/vus/utils/metrics.py
TSB_UAD-0.0.3.dist-info/LICENSE
TSB_UAD-0.0.3.dist-info/METADATA
TSB_UAD-0.0.3.dist-info/WHEEL
TSB_UAD-0.0.3.dist-info/top_level.txt
TSB_UAD-0.0.3.dist-info/zip-safe
TSB_UAD-0.0.3.dist-info/RECORD
